LICENSE
MANIFEST.in
README.md
setup.cfg
setup.py
versioneer.py
ensembler/__init__.py
ensembler/__version__.py
ensembler/_version.py
ensembler/ensembler.py
ensembler/analysis/__init__.py
ensembler/analysis/freeEnergyCalculation.py
ensembler/conditions/__init__.py
ensembler/conditions/_basicCondition.py
ensembler/conditions/box_conditions.py
ensembler/conditions/restrain_conditions.py
ensembler/conditions/thermostats.py
ensembler/data/README.md
ensembler/ensemble/__init__.py
ensembler/ensemble/_replica_graph.py
ensembler/ensemble/exchange_pattern.py
ensembler/ensemble/replica_exchange.py
ensembler/ensemble/replicas_dynamic_parameters.py
ensembler/potentials/ND.py
ensembler/potentials/OneD.py
ensembler/potentials/TwoD.py
ensembler/potentials/__init__.py
ensembler/potentials/_basicPotentials.py
ensembler/samplers/__init__.py
ensembler/samplers/_basicSamplers.py
ensembler/samplers/newtonian.py
ensembler/samplers/optimizers.py
ensembler/samplers/stochastic.py
ensembler/system/__init__.py
ensembler/system/basic_system.py
ensembler/system/eds_system.py
ensembler/system/perturbed_system.py
ensembler/tests/__init__.py
ensembler/tests/test_analysis.py
ensembler/tests/test_conditions.py
ensembler/tests/test_conveyorBelt.py
ensembler/tests/test_ensemble.py
ensembler/tests/test_ensembler.py
ensembler/tests/test_potentials.py
ensembler/tests/test_sampler.py
ensembler/tests/test_system.py
ensembler/tests/test_visualization.py
ensembler/util/__init__.py
ensembler/util/basic_class.py
ensembler/util/dataStructure.py
ensembler/util/ensemblerTypes.py
ensembler/visualisation/__init__.py
ensembler/visualisation/animationSimulation.py
ensembler/visualisation/interactive_plots.py
ensembler/visualisation/plotConveyorBelt.py
ensembler/visualisation/plotPotentials.py
ensembler/visualisation/plotSimulations.py
ensembler/visualisation/style.py
ensembler_rinikerlab.egg-info/PKG-INFO
ensembler_rinikerlab.egg-info/SOURCES.txt
ensembler_rinikerlab.egg-info/dependency_links.txt
ensembler_rinikerlab.egg-info/requires.txt
ensembler_rinikerlab.egg-info/top_level.txt