Metadata-Version: 2.1
Name: ensembler-rinikerlab
Version: 1.0.4
Summary: UNKNOWN
Home-page: https://github.com/rinikerlab/Ensembler
Author: Benjamin Ries; David Friedrich Hahn; Stephanie Linker
Author-email: bschroed@ethz.ch
License: MIT
Download-URL: https://github.com/rinikerlab/Ensembler/archive/1.0.tar.gz
Keywords: teaching method_development statistical_mechanics statistical_thermodynamics physics chemistry free_energy_calculations free energy enhanced sampling RE-EDS EDS Conveyor_Belt_TI numerical_integration science
Platform: Linux
Platform: Mac OS-X
Platform: Unix
Platform: Windows
Requires-Python: >=3.5
Provides-Extra: docs
